simplest_conf_manager/.idea/.gitignore
simplest_conf_manager/.idea/conf_manager.iml
simplest_conf_manager/.idea/inspectionProfiles/profiles_settings.xml
simplest_conf_manager/.idea/inspectionProfiles/Project_Default.xml
simplest_conf_manager/.idea/jupyter-settings.xml
simplest_conf_manager/.idea/misc.xml
simplest_conf_manager/.idea/modules.xml
simplest_conf_manager/__init__.py
simplest_conf_manager/base_config.py
simplest_conf_manager/base_strings.py
simplest_conf_manager/translator.py
simplest_conf_manager/utils/data_providers/__init__.py
simplest_conf_manager/utils/data_providers/base_data_provider.py
simplest_conf_manager/utils/data_providers/base_multi_data_provider.py
simplest_conf_manager/utils/data_providers/file_data_provider.py
simplest_conf_manager/utils/data_providers/folder_data_provider.py
simplest_conf_manager/utils/dictionaries/__init__.py
simplest_conf_manager/utils/dictionaries/deep_merge.py
simplest_conf_manager/utils/parsers/__init__.py
simplest_conf_manager/utils/parsers/base_parser.py
simplest_conf_manager/utils/parsers/toml_parser.py
simplest_conf_manager-0.1.2.1.dist-info/METADATA
simplest_conf_manager-0.1.2.1.dist-info/WHEEL
simplest_conf_manager-0.1.2.1.dist-info/RECORD
