Metadata-Version: 2.1
Name: simplest-conf-manager
Version: 0.1.2.1
Summary: 
Author: matthew-shtyasek
Author-email: shtyasek2003@mail.ru
Requires-Python: >=3.12,<4.0
Classifier: Programming Language :: Python :: 3
Classifier: Programming Language :: Python :: 3.12
Requires-Dist: pydantic (>=2.8.2,<3.0.0)
Requires-Dist: setuptools (>=70.3.0,<71.0.0)
Requires-Dist: toml (>=0.10.2,<0.11.0)
